PROJ/PROJECT2/src/dataMemory.v
`ifndef MODULE_DATA_MEMORY
`define MODULE_DATA_MEMORY
module dataMemory (
	input 			clk,    
	input	[31:0]	address,
					writeData,
	input			memRead,
					memWrite,
	output	[31:0]	readData
	
);

	// numbers of memory the program wants
	parameter nums = 32;
	wire 	[31:0]	index;
	reg		[31:0]	memory [0:nums-1];
	integer 		i;

	assign index = address >> 2;
	
	initial begin
		for(i = 0; i < nums; i = i + 1)
			memory[i] = 32'b0;
	end

	always @(negedge clk ) begin
		if (memWrite == 1'b1) begin
			 memory[index] = writeData;
		end
	end

	assign readData = (memRead == 1'b1) ? memory[index]:32'b0; 
	

endmodule

`endif

PROJ/PROJECT2/370report/singlecycle/ALU.v
`ifndef MODULE_ALU
`define MODULE_ALU
`timescale 1ns / 1ps

module ALU (
    input       [3:0]   control,
    input       [31:0]  a, b,
    output              zero,
    output reg  [31:0]  result
);

    assign zero = (result == 0);

    initial begin
        result = 32'b0;
    end

    always @ (*) begin
        case (control)
            4'b0000: // AND
                result = a & b;
            4'b0001: // OR
                result = a | b;
            4'b0010: // ADD
                result = a + b;
            4'b0110: // SUB
                result = a - b;
            4'b0111: // SLT
                result = (a < b) ? 1 : 0;
            4'b1100: // NOR
                result = ~(a | b);
            default: ;
        endcase
    end

endmodule 

`endif

PROJ/PROJECT2/370report/singlecycle/ALUControl.v
`ifndef MODULE_ALU_CONTROL
`define MODULE_ALU_CONTROL

module ALUControl (
	input 		[1:0]	ALUop,
	input 		[5:0]	funct,
	output reg	[3:0]	control	
);
	always @(*) begin
		case (ALUop)
			2'b00: 
				control = 4'b0010;
			2'b01:
				control = 4'b0110;
			2'b10:
				case (funct)
					6'b100000:
						control = 4'b0010;
					6'b100010:
						control = 4'b0110;
					6'b100100:
						control = 4'b0000;
					6'b100101:
						control = 4'b0001;
					6'b101010:
						control = 4'b0111;
					default : ;
				endcase
			2'b11:
				control = 4'b0000;
			default : ;
		endcase
	end

endmodule

`endif

PROJ/PROJECT2/src/signExtend.v
`ifndef MODULE_SIGN_EXTEND
`define MODULE_SIGN_EXTEND

module signExtend (
	input	[15:0]	in,
	output	[31:0]	out
);

	assign out = {{16{in[15]}},in[15:0]};

endmodule

`endif

PROJ/PROJECT2/src/register.v
`ifndef MODULE_REGISTER
`define MODULE_REGISTER
`timescale 1ns / 1ps

module register (
	input			clk, _regWrite,
	input	[4:0]	readReg1, 
					readReg2,
					writeReg,
	input	[31:0]	writeData,
	output	[31:0]	readData1,readData2
	
);
	reg 	[31:0] 	regs [0:31];
	integer i;
	initial begin
		for(i = 0 ; i < 32;i = i+1) begin
			regs[i] = 32'b0;
		end
	end

	assign readData1 = regs[readReg1];
	assign readData2 = regs[readReg2];
	always @(negedge clk ) begin
		if(_regWrite == 1'b1) begin
			 regs[writeReg] <= writeData;
		end
	end

endmodule

`endif

PROJ/PROJECT2/370report/singlecycle/Control.v
`ifndef MODULE_CONTROL
`define MODULE_CONTROL
`timescale 1ns / 1ps

module Control (
    input       [5:0]   opCode,
    output reg          regDst,
                        jump,
                        beq,
                        bne,
                        memRead,
                        memtoReg,
                        memWrite,
                        ALUSrc,
                        regWrite,
    output reg  [1:0]   ALUOp
);

    initial begin
        regDst      = 1'b0;
        jump        = 1'b0;
        beq         = 1'b0;
        bne         = 1'b0;
        memRead     = 1'b0;
        memtoReg    = 1'b0;
        memWrite    = 1'b0;
        ALUSrc      = 1'b0;
        regWrite    = 1'b0;
        ALUOp       = 2'b00;
    end

    always @ (opCode) begin
        case (opCode)
            6'b000000: begin // R-type
                regDst      <= 1'b1;
                jump        <= 1'b0;
                beq         <= 1'b0;
                bne         <= 1'b0;
                memRead     <= 1'b0;
                memtoReg    <= 1'b0;
                memWrite    <= 1'b0;
                ALUSrc      <= 1'b0;
                regWrite    <= 1'b1;
                ALUOp       <= 2'b10;
            end
            6'b000010: begin // j-type
                regDst      <= 1'b1;
                jump        <= 1'b1;
                beq         <= 1'b0;
                bne         <= 1'b0;
                memRead     <= 1'b0;
                memtoReg    <= 1'b0;
                memWrite    <= 1'b0;
                ALUSrc      <= 1'b0;
                regWrite    <= 1'b0;
                ALUOp       <= 2'b10;
            end
            6'b000100: begin // beq
                regDst      <= 1'b1;
                jump        <= 1'b0;
                beq         <= 1'b1;
                bne         <= 1'b0;
                memRead     <= 1'b0;
                memtoReg    <= 1'b0;
                memWrite    <= 1'b0;
                ALUSrc      <= 1'b0;
                regWrite    <= 1'b0;
                ALUOp       <= 2'b01;
            end
            6'b000101: begin // bne
                regDst      <= 1'b1;
                jump        <= 1'b0;
                beq         <= 1'b0;
                bne         <= 1'b1;
                memRead     <= 1'b0;
                memtoReg    <= 1'b0;
                memWrite    <= 1'b0;
                ALUSrc      <= 1'b0;
                regWrite    <= 1'b0;
                ALUOp       <= 2'b01;
            end
            6'b001000: begin // addi
                regDst      <= 1'b0;
                jump        <= 1'b0;
                beq         <= 1'b0;
                bne         <= 1'b0;
                memRead     <= 1'b0;
                memtoReg    <= 1'b0;
                memWrite    <= 1'b0;
                ALUSrc      <= 1'b1;
                regWrite    <= 1'b1;
                ALUOp       <= 2'b00;
            end
            6'b001100: begin // andi
                regDst      <= 1'b0;
                jump        <= 1'b0;
                beq         <= 1'b0;
                bne         <= 1'b0;
                memRead     <= 1'b0;
                memtoReg    <= 1'b0;
                memWrite    <= 1'b0;
                ALUSrc      <= 1'b1;
                regWrite    <= 1'b1;
                ALUOp       <= 2'b11;
            end
            6'b100011: begin // lw
                regDst      <= 1'b0;
                jump        <= 1'b0;
                beq         <= 1'b0;
                bne         <= 1'b0;
                memRead     <= 1'b1;
                memtoReg    <= 1'b1;
                memWrite    <= 1'b0;
                ALUSrc      <= 1'b1;
                regWrite    <= 1'b1;
                ALUOp       <= 2'b00;
            end
            6'b101011: begin // sw
                regDst      <= 1'b0;
                jump        <= 1'b0;
                beq         <= 1'b0;
                bne         <= 1'b0;
                memRead     <= 1'b0;
                memtoReg    <= 1'b0;
                memWrite    <= 1'b1;
                ALUSrc      <= 1'b1;
                regWrite    <= 1'b0;
                ALUOp       <= 2'b00;
            end

            default: ;
        endcase
    end

endmodule 

`endif

PROJ/PROJECT2/src/instructionMemory.v
`ifndef MODULE_INSTRUCTION_MEMEORY
`define MODULE_INSTRUCTION_MEMEORY
`timescale 1ns / 1ps
module instructionMemory (
	input	[31:0]	address,
	output	[31:0]	instruction
);
	// I really don't know how to get this num. At least 40 space is enough for this input file.
	parameter size = 40;
	reg	[31:0]	memory [0:size - 1];
	integer i;

	initial begin
		for(i = 0 ; i<size;i=i+1) begin
			memory[i] = 32'b0;
		end
		`include "InstructionMem_for_P2_Demo.txt"
	end

	assign instruction = memory[address >> 2];
endmodule

`endif

PROJ/PROJECT2/370report/pipeline/PC.v
`ifndef MODULE_PC
`define MODULE_PC
`timescale 1ns / 1ps

module PC(
    input       clk,stall,
    input       [31:0]  in,
    output reg  [31:0]  out
    );
    
    initial begin
        out = 32'b0; //initialize PC
    end
    
    always @ (posedge clk) begin
        if (!stall)
            out <= in;
    end
    
endmodule
`endif

PROJ/PROJECT2/370report/singlecycle/singleCycle.v
`ifndef MODULE_SINGLE_CYCLE
`define MODULE_SINGLE_CYCLE
`timescale 1ns / 1ps
`include "ALU.v"
`include "ALUControl.v"
`include "Control.v"
`include "dataMemory.v"
`include "PC.v"
`include "register.v"
`include "signExtend.v"
`include "instructionMemory.v"

module singleCycle (input clk);
    //insturction and PC
    wire    [31:0]  instruction,
                    pc_in,
    				pc_out,
                    next_instruction_addr,
                    jump_addr,
                    next_addr;

    //control unit, all vars start with _
    wire            _reg_write,
                    _ALU_src,
                    _branch,
                    _jump,
                    _beq,
                    _bne,
                    _reg_dst,
                    _mem_to_reg,
                    _mem_read,
                    _mem_write;

    //register
    wire    [31:0]  read_reg_data_1,
                    read_reg_data_2,
                    write_data;
    wire    [4:0]   write_reg;

    // sign_extend output
    wire    [31:0]  sign_extend_output;

    //ALU control
    wire    [1:0]   ALU_op;
    wire    [3:0]   ALU_control;

    //ALU
    wire    [31:0]  ALU_second_input,
                    ALU_result;
    wire            ALU_zero_ouput;
 
    // dataMemory
    wire    [31:0]  data_memory_read_data;

    // MUX for next instructions
    assign next_addr = pc_out + 4;
    assign _branch = (ALU_zero_ouput & _beq) | (~ALU_zero_ouput & _bne);
    assign next_instruction_addr = (_branch == 1'b0) ? next_addr : next_addr + (sign_extend_output << 2 );
    assign jump_addr = {next_addr[31:28],instruction[25:0],2'b0};
    assign pc_in = (_jump == 1'b0) ? next_instruction_addr : jump_addr;
    //MUX for which register to be written 
    assign write_reg = (_reg_dst == 1'b0) ? instruction[20:16] : instruction[15:11];
    //MUX for which data to be written into register
    assign write_data = (_mem_to_reg == 1'b0) ? ALU_result : data_memory_read_data;
    //MUX for which data to be the second input of ALU
    assign ALU_second_input = (_ALU_src == 1'b0) ?  read_reg_data_2 : sign_extend_output;

    PC ShiLi(
    	.clk(clk),
    	.in(pc_in),
    	.out(pc_out)
    );

    instructionMemory VE370highShiLi(
        .address    (pc_out),
        .instruction(instruction)
    );

    Control  KingofEE_ShiJian(
        .opCode  (instruction[31:26]),
        .regDst  (_reg_dst),
        .jump    (_jump),
        .beq     (_beq),
        .bne     (_bne),
        .memRead (_mem_read),
        .memWrite(_mem_write),
        .memtoReg(_mem_to_reg),
        .ALUSrc  (_ALU_src),
        .regWrite(_reg_write),
        .ALUOp   (ALU_op)
    );
 
    register ktt(
    	.clk      (clk),
    	._regWrite (_reg_write),
    	.readReg1 (instruction[25:21]),
    	.readReg2 (instruction[20:16]),
    	.writeReg (write_reg),
    	.writeData(write_data),
        .readData1(read_reg_data_1),
        .readData2(read_reg_data_2)
    );

    signExtend UniverseNoOneSHiLi(
        .in (instruction[15:0]),
        .out(sign_extend_output)
    );

    ALUControl MostLearn_ShiJian(
    	.ALUop  (ALU_op),
    	.funct  (instruction[5:0]),
    	.control(ALU_control)
    );

    ALU Manuel(
        .control(ALU_control),
        .a      (read_reg_data_1),
        .b      (ALU_second_input),
        .zero   (ALU_zero_ouput),
        .result (ALU_result)
    );

    dataMemory zzz(
    	.clk      (clk),
    	.address  (ALU_result),
    	.memRead  (_mem_read),
    	.memWrite (_mem_write),
    	.writeData(read_reg_data_2),
    	.readData (data_memory_read_data)
    );

endmodule

`endif

PROJ/PROJECT2/src/test_bench.v
`timescale 1ns / 1ps
`include "singleCycle.v"

module singleCycleTestBench;

    integer i = 0;
	reg clk;

	singleCycle uut (
		.clk(clk)
	);

	initial begin
		clk = 0;
        $dumpfile("singleCycle.vcd");
        $dumpvars(1, uut);
        $display("Result of single cycle simulation:");
        $display("==========================================================");
        #500;
        $stop;
	end

    always #10 begin
        $display("Time: %d ns, Clock = %d, PC = 0x%H", i, clk, uut.pc_out);
        $display("[$s0] = 0x%H, [$s1] = 0x%H, [$s2] = 0x%H", uut.ktt.regs[16], uut.ktt.regs[17], uut.ktt.regs[18]);
        $display("[$s3] = 0x%H, [$s4] = 0x%H, [$s5] = 0x%H", uut.ktt.regs[19], uut.ktt.regs[20], uut.ktt.regs[21]);
        $display("[$s6] = 0x%H, [$s7] = 0x%H, [$t0] = 0x%H", uut.ktt.regs[22], uut.ktt.regs[23], uut.ktt.regs[8]);
        $display("[$t1] = 0x%H, [$t2] = 0x%H, [$t3] = 0x%H", uut.ktt.regs[9], uut.ktt.regs[10], uut.ktt.regs[11]);
        $display("----------------------------------------------------------");
        clk = ~clk;
        i = i + 10;
    end

endmodule

PROJ/PROJECT2/src/singleCycle.vcd
$date
	Sun Oct 27 16:17:09 2019
$end
$version
	Icarus Verilog
$end
$timescale
	1ps
$end
$scope module singleCycleTestBench $end
$scope module uut $end
$var wire 1 ! _branch $end
$var wire 1 " clk $end
$var wire 5 # write_reg [4:0] $end
$var wire 32 $ write_data [31:0] $end
$var wire 32 % sign_extend_output [31:0] $end
$var wire 32 & read_reg_data_2 [31:0] $end
$var wire 32 ' read_reg_data_1 [31:0] $end
$var wire 32 ( pc_out [31:0] $end
$var wire 32 ) pc_in [31:0] $end
$var wire 32 * next_instruction_addr [31:0] $end
$var wire 32 + next_addr [31:0] $end
$var wire 32 , jump_addr [31:0] $end
$var wire 32 - instruction [31:0] $end
$var wire 32 . data_memory_read_data [31:0] $end
$var wire 1 / _reg_write $end
$var wire 1 0 _reg_dst $end
$var wire 1 1 _mem_write $end
$var wire 1 2 _mem_to_reg $end
$var wire 1 3 _mem_read $end
$var wire 1 4 _jump $end
$var wire 1 5 _bne $end
$var wire 1 6 _beq $end
$var wire 1 7 _ALU_src $end
$var wire 1 8 ALU_zero_ouput $end
$var wire 32 9 ALU_second_input [31:0] $end
$var wire 32 : ALU_result [31:0] $end
$var wire 2 ; ALU_op [1:0] $end
$var wire 4 < ALU_control [3:0] $end
$upscope $end
$upscope $end
$enddefinitions $end
#0
$dumpvars
b10 <
b0 ;
b100000 :
b100000 9
08
17
06
05
04
03
02
01
00
1/
b0 .
b100000000010000000000000100000 -
b1000000000000010000000 ,
b100 +
b100 *
b100 )
b0 (
b0 '
b0 &
b100000 %
b100000 $
b1000 #
0"
0!
$end
#10000
b110111 $
b110111 :
b110111 9
b1001 #
b110111 %
b1001000000000011011100 ,
b1000 )
b100000000010010000000000110111 -
b1000 *
b1000 +
b100 (
1"
#20000
b110111 &
0"
#30000
18
b10000 #
b0 <
b10 ;
07
10
b0 $
b0 :
b110111 9
b11111111111111111000000000100100 %
b100001001100000000010010000 ,
b1100 )
b1000010011000000000100100 -
b1100 *
b1100 +
b1000 (
1"
#40000
0"
#50000
b110111 $
08
b110111 :
b1 <
b11111111111111111000000000100101 %
b100001001100000000010010100 ,
b10000 )
b1000010011000000000100101 -
b10000 *
b10000 +
b1100 (
1"
#60000
0"
#70000
b100 $
b100 :
b100 9
b10 <
b0 ;
0/
17
11
00
b10000 #
b100 %
b10000000000000000010000 ,
b10100 )
b10101100000100000000000000000100 -
b10100 *
b10100 +
b10000 (
1"
#80000
0"
#90000
b1000 $
b1000 :
b1000 9
b1000 #
b1000 %
b0 &
b1000000000000000100000 ,
b11000 )
b10101100000010000000000000001000 -
b11000 *
b11000 +
b10100 (
1"
#100000
0"
#110000
b10 ;
1/
07
01
10
b110111 $
b110111 :
b110111 9
b10001 #
b11111111111111111000100000100000 %
b110111 &
b100001001100010000010000000 ,
b11100 )
b1000010011000100000100000 -
b11100 *
b11100 +
b11000 (
1"
#120000
0"
#130000
b11111111111111111111111111001001 $
b11111111111111111111111111001001 :
b110 <
b10010 #
b11111111111111111001000000100010 %
b100001001100100000010001000 ,
b100000 )
b1000010011001000000100010 -
b100000 *
b100000 +
b11100 (
1"
#140000
0"
#150000
b1 ;
0/
16
b1101110 $
b11111111111111111111111111001001 9
08
b1101110 :
b0 #
b1001 %
b11111111111111111111111111001001 &
b110111 '
b1000110010000000000000100100 ,
b100100 )
b10010001100100000000000001001 -
b100100 *
b100100 +
b100000 (
1"
#160000
0"
#170000
b110111 .
b10001 #
b10 <
b0 ;
1/
17
12
13
06
00
b110111 $
b100 9
b100 :
b100 %
b110111 &
b0 '
b10001000000000000010000 ,
b101000 )
b10001100000100010000000000000100 -
b101000 *
b101000 +
b100100 (
1"
#180000
0"
#190000
18
b0 <
b11 ;
02
03
b0 $
b0 .
b1001000 9
b0 :
b10010 #
b1001000 %
b11111111111111111111111111001001 &
b110111 '
b1000110010000000000100100000 ,
b101100 )
b110010001100100000000001001000 -
b101100 *
b101100 +
b101000 (
1"
#200000
b0 &
0"
#210000
b0 #
b110 <
b1 ;
0/
07
16
10
b110111 $
08
b110111 :
b0 9
b1001 %
b1000110010000000000000100100 ,
b110000 )
b10010001100100000000000001001 -
b110000 *
b110000 +
b101100 (
1"
#220000
0"
#230000
b1000 9
b10011 #
b10 <
b0 ;
1/
17
12
13
06
00
0!
b0 $
08
b1000 :
b1000 %
b0 '
b10011000000000000100000 ,
b110100 )
b10001100000100110000000000001000 -
b110100 *
b110100 +
b110000 (
1"
#240000
0"
#250000
b110111 $
b0 #
b110 <
b1 ;
0/
07
02
03
16
10
b0 9
b110111 :
b1010 %
b110111 '
b1000010011000000000000101000 ,
b111000 )
b10010000100110000000000001010 -
b111000 *
b111000 +
b110100 (
1"
#260000
0"
#270000
b111 <
b10 ;
1/
06
0!
b1 $
b110111 9
08
b1 :
b10100 #
b11111111111111111010000000101010 %
b110111 &
b0 '
b1001010001101000000010101000 ,
b111100 )
b10010100011010000000101010 -
b111100 *
b111100 +
b111000 (
1"
#280000
0"
#290000
0!
b110 <
b1 ;
0/
16
b1 $
08
b1 :
b0 9
b0 #
b1111 %
b0 &
b1 '
b1010000000000000000000111100 ,
b1000000 )
b10010100000000000000000001111 -
b1000000 *
b1000000 +
b111100 (
1"
#300000
0"
#310000
b10 <
b10 ;
1/
06
b110111 $
b110111 :
b10010 #
b11111111111111111001000000100000 %
b110111 '
b1000100000100100000010000000 ,
b1000100 )
b10001000001001000000100000 -
b1000100 *
b1000100 +
b1000000 (
1"
#320000
0"
#330000
0/
14
b0 $
18
b0 :
b0 #
b1110 %
b0 '
b111000 ,
b111000 )
b1000000000000000000000001110 -
b1001000 *
b1001000 +
b1000100 (
1"
#340000
0"
#350000
1/
04
b0 $
b111 <
b110111 9
18
b0 :
b10100 #
b111100 )
b11111111111111111010000000101010 %
b110111 &
b110111 '
b1001010001101000000010101000 ,
b10010100011010000000101010 -
b111100 *
b111100 +
b111000 (
1"
#360000
0"
#370000
1!
b110 <
b1 ;
0/
16
b0 $
b0 9
18
b0 :
b0 #
b1111 %
b0 &
b0 '
b1010000000000000000000111100 ,
b1111100 )
b10010100000000000000000001111 -
b1111100 *
b1000000 +
b111100 (
1"
#380000
0"
#390000
0!
b10 ;
1/
06
b0 %
b0 ,
b10000000 )
b0 -
b10000000 *
b10000000 +
b1111100 (
1"
#400000
0"
#410000
b10000100 )
b10000100 *
b10000100 +
b10000000 (
1"
#420000
0"
#430000
b10001000 )
b10001000 *
b10001000 +
b10000100 (
1"
#440000
0"
#450000
b10001100 )
b10001100 *
b10001100 +
b10001000 (
1"
#460000
0"
#470000
b10010000 )
b10010000 *
b10010000 +
b10001100 (
1"
#480000
0"
#490000
b10010100 )
b10010100 *
b10010100 +
b10010000 (
1"
